minilanguage/__init__.py
minilanguage/grammar.py
minilanguage/lexer.py
minilanguage/lextab.py
minilanguage/parsetab.py
minilanguage-2.0.0.dist-info/DESCRIPTION.rst
minilanguage-2.0.0.dist-info/METADATA
minilanguage-2.0.0.dist-info/RECORD
minilanguage-2.0.0.dist-info/WHEEL
minilanguage-2.0.0.dist-info/metadata.json
minilanguage-2.0.0.dist-info/top_level.txt
