Metadata-Version: 2.0
Name: minilanguage
Version: 2.0.0
Summary: A minimal DSL for Python
Home-page: https://github.com/fcurella/minilanguage/
Author: Flavio Curella
Author-email: flavio.curella@gmail.com
License: MIT
Platform: any
Classifier: Development Status :: 5 - Production/Stable
Classifier: License :: OSI Approved :: MIT License
Classifier: Operating System :: OS Independent
Classifier: Programming Language :: Python
Classifier: Programming Language :: Python :: 2
Classifier: Programming Language :: Python :: 2.7
Classifier: Programming Language :: Python :: 3
Classifier: Programming Language :: Python :: 3.4
Classifier: Programming Language :: Python :: 3.5
Classifier: Programming Language :: Python :: 3.6
Requires-Dist: ply (>=3)
